eri/__init__.py
eri/bootstrap.py
eri/cache.py
eri/colors.py
eri/decorators.py
eri/graph.py
eri/regex.py
eri/string.py
eri/transform.py
eri/util.py
eri/weighted_bootstrap_sampling.py
eri/clean/__init__.py
eri/config/eriproj.yaml
eri/dash/__init__.py
eri/dash/bootstrap.py
eri/html/__init__.py
eri/html/utils.py
eri/logging/__init__.py
eri/logging/default.yaml
eri/visualization/__init__.py
eri/visualization/colors.py
eri/visualization/words.py
eri-0.1.5.dist-info/METADATA
eri-0.1.5.dist-info/RECORD
eri-0.1.5.dist-info/WHEEL
eri-0.1.5.dist-info/entry_points.txt
eri-0.1.5.dist-info/top_level.txt
