Metadata-Version: 2.1
Name: eri
Version: 0.1.5
Summary: Common functionality for data science at ERI
Home-page: http://elderresearch.com/
Author: Zach Lamberty
Author-email: zach.lamberty@elderresearch.com
License: MIT
Keywords: data science
Platform: UNKNOWN
Classifier: Development Status :: 3 - Alpha
Classifier: Intended Audience :: Science/Research
Classifier: Topic :: Scientific/Engineering
Classifier: License :: OSI Approved :: MIT License
Classifier: Programming Language :: Python :: 3
Classifier: Programming Language :: Python :: 3.2
Classifier: Programming Language :: Python :: 3.3
Classifier: Programming Language :: Python :: 3.4
Classifier: Programming Language :: Python :: 3.5
Provides-Extra: test
Requires-Dist: colorlog (>=2.7.0)
Requires-Dist: jupyter (>=1.0.0)
Requires-Dist: lxml (>=3.6.0)
Requires-Dist: missingno (>=0.3.7)
Requires-Dist: pandas (>=0.18.1)
Requires-Dist: pyyaml (>=3.11)
Requires-Dist: requests (>=2.10.0)
Requires-Dist: seaborn (>=0.7.0)
Provides-Extra: test
Requires-Dist: nose; extra == 'test'
